[
  {
    "grammarPoint": "Tính từ i / na",
    "examples": [
      {
        "sentence": "田中さんはハンサムです。",
        "translation": "Anh Tanaka đẹp trai.",
        "translationEn": "Mr. Tanaka is handsome."
      },
      {
        "sentence": "この部屋はきれいです。",
        "translation": "Căn phòng này sạch đẹp.",
        "translationEn": "This room is clean and beautiful."
      },
      {
        "sentence": "この町は賑やかです。",
        "translation": "Thị trấn này náo nhiệt.",
        "translationEn": "This town is lively."
      },
      {
        "sentence": "この公園は静かです。",
        "translation": "Công viên này yên tĩnh.",
        "translationEn": "This park is quiet."
      },
      {
        "sentence": "京都は有名です。",
        "translation": "Kyoto nổi tiếng.",
        "translationEn": "Kyoto is famous."
      },
      {
        "sentence": "このかばんは便利です。",
        "translation": "Cái cặp này tiện lợi.",
        "translationEn": "This bag is convenient."
      },
      {
        "sentence": "ミラーさんは元気です。",
        "translation": "Anh Miller khỏe mạnh.",
        "translationEn": "Mr. Miller is well."
      },
      {
        "sentence": "この本はおもしろいです。",
        "translation": "Quyển sách này thú vị.",
        "translationEn": "This book is interesting."
      },
      {
        "sentence": "今日は寒いです。",
        "translation": "Hôm nay trời lạnh.",
        "translationEn": "It is cold today."
      },
      {
        "sentence": "この食べ物はおいしいです。",
        "translation": "Món ăn này ngon.",
        "translationEn": "This food is delicious."
      }
    ]
  },
  {
    "grammarPoint": "Aくない, Aじゃない (Phủ định tính từ)",
    "examples": [
      {
        "sentence": "今日は寒くないです。",
        "translation": "Hôm nay trời không lạnh.",
        "translationEn": "It is not cold today."
      },
      {
        "sentence": "この部屋は静かじゃありません。",
        "translation": "Căn phòng này không yên tĩnh.",
        "translationEn": "This room is not quiet."
      },
      {
        "sentence": "その町は便利じゃありません。",
        "translation": "Thị trấn đó không tiện lợi.",
        "translationEn": "That town is not convenient."
      },
      {
        "sentence": "この本はおもしろくないです。",
        "translation": "Quyển sách này không thú vị.",
        "translationEn": "This book is not interesting."
      },
      {
        "sentence": "このかばんは高くないです。",
        "translation": "Cái cặp này không đắt.",
        "translationEn": "This bag is not expensive."
      },
      {
        "sentence": "あの山は低くないです。",
        "translation": "Ngọn núi kia không thấp.",
        "translationEn": "That mountain is not low."
      },
      {
        "sentence": "田中さんは暇じゃありません。",
        "translation": "Anh Tanaka không rảnh.",
        "translationEn": "Mr. Tanaka is not free."
      },
      {
        "sentence": "このシャツは新しくないです。",
        "translation": "Chiếc áo này không mới.",
        "translationEn": "This shirt is not new."
      },
      {
        "sentence": "その食べ物はおいしくないです。",
        "translation": "Món ăn đó không ngon.",
        "translationEn": "That food is not delicious."
      },
      {
        "sentence": "あの店は有名じゃありません。",
        "translation": "Cửa hàng kia không nổi tiếng.",
        "translationEn": "That shop is not famous."
      }
    ]
  },
  {
    "grammarPoint": "Aな N, Aい N",
    "examples": [
      {
        "sentence": "田中さんは親切な先生です。",
        "translation": "Anh Tanaka là một giáo viên tử tế.",
        "translationEn": "Mr. Tanaka is a kind teacher."
      },
      {
        "sentence": "そこは静かな町です。",
        "translation": "Đó là một thị trấn yên tĩnh.",
        "translationEn": "That is a quiet town."
      },
      {
        "sentence": "ここは賑やかな食堂です。",
        "translation": "Đây là một nhà ăn nhộn nhịp.",
        "translationEn": "This is a lively dining hall."
      },
      {
        "sentence": "これはきれいな桜です。",
        "translation": "Đây là hoa anh đào đẹp.",
        "translationEn": "These are beautiful cherry blossoms."
      },
      {
        "sentence": "あれは新しいかばんです。",
        "translation": "Kia là cái cặp mới.",
        "translationEn": "That is a new bag."
      },
      {
        "sentence": "それは古い本です。",
        "translation": "Đó là một quyển sách cũ.",
        "translationEn": "That is an old book."
      },
      {
        "sentence": "これはおいしい食べ物です。",
        "translation": "Đây là món ăn ngon.",
        "translationEn": "This is delicious food."
      },
      {
        "sentence": "あの山は大きい山です。",
        "translation": "Ngọn núi kia là ngọn núi lớn.",
        "translationEn": "That is a big mountain."
      },
      {
        "sentence": "ここは小さい町です。",
        "translation": "Đây là một thị trấn nhỏ.",
        "translationEn": "This is a small town."
      },
      {
        "sentence": "その寮は便利な寮です。",
        "translation": "Ký túc xá đó là ký túc xá tiện lợi.",
        "translationEn": "That is a convenient dormitory."
      }
    ]
  },
  {
    "grammarPoint": "～が、～ (Nhưng)",
    "examples": [
      {
        "sentence": "この町は賑やかですが、私のうちは静かです。",
        "translation": "Thị trấn này nhộn nhịp, nhưng nhà tôi yên tĩnh.",
        "translationEn": "This town is lively, but my home is quiet."
      },
      {
        "sentence": "この本はおもしろいですが、少し難しいです。",
        "translation": "Quyển sách này thú vị, nhưng hơi khó.",
        "translationEn": "This book is interesting, but it is a little difficult."
      },
      {
        "sentence": "この食べ物はおいしいですが、少し辛いです。",
        "translation": "Món ăn này ngon, nhưng hơi cay.",
        "translationEn": "This food is delicious, but it is a little spicy."
      },
      {
        "sentence": "今日は寒いですが、天気はいいです。",
        "translation": "Hôm nay trời lạnh, nhưng thời tiết đẹp.",
        "translationEn": "It is cold today, but the weather is nice."
      },
      {
        "sentence": "このかばんは高いですが、とてもすてきです。",
        "translation": "Cái cặp này đắt, nhưng rất đẹp.",
        "translationEn": "This bag is expensive, but it is very lovely."
      },
      {
        "sentence": "あの寮は古いですが、便利です。",
        "translation": "Ký túc xá kia cũ, nhưng tiện lợi.",
        "translationEn": "That dormitory is old, but it is convenient."
      },
      {
        "sentence": "田中さんは忙しいですが、元気です。",
        "translation": "Anh Tanaka bận, nhưng khỏe mạnh.",
        "translationEn": "Mr. Tanaka is busy, but he is energetic."
      },
      {
        "sentence": "この町は有名ですが、大きくないです。",
        "translation": "Thị trấn này nổi tiếng, nhưng không lớn.",
        "translationEn": "This town is famous, but it is not big."
      },
      {
        "sentence": "この山は高いですが、きれいです。",
        "translation": "Ngọn núi này cao, nhưng đẹp.",
        "translationEn": "This mountain is high, but beautiful."
      },
      {
        "sentence": "この部屋は小さいですが、きれいです。",
        "translation": "Căn phòng này nhỏ, nhưng sạch đẹp.",
        "translationEn": "This room is small, but clean and nice."
      }
    ]
  },
  {
    "grammarPoint": "とても, あまり (Mức độ)",
    "examples": [
      {
        "sentence": "この町はとても賑やかです。",
        "translation": "Thị trấn này rất nhộn nhịp.",
        "translationEn": "This town is very lively."
      },
      {
        "sentence": "今日はあまり寒くないです。",
        "translation": "Hôm nay trời không lạnh lắm.",
        "translationEn": "It is not very cold today."
      },
      {
        "sentence": "ワット先生はとても親切です。",
        "translation": "Thầy Watt rất tử tế.",
        "translationEn": "Mr. Watt is very kind."
      },
      {
        "sentence": "この部屋はあまり静かじゃありません。",
        "translation": "Căn phòng này không yên tĩnh lắm.",
        "translationEn": "This room is not very quiet."
      },
      {
        "sentence": "この本はとてもおもしろいです。",
        "translation": "Quyển sách này rất thú vị.",
        "translationEn": "This book is very interesting."
      },
      {
        "sentence": "その食べ物はあまりおいしくないです。",
        "translation": "Món ăn đó không ngon lắm.",
        "translationEn": "That food is not very delicious."
      },
      {
        "sentence": "この寮はとても便利です。",
        "translation": "Ký túc xá này rất tiện lợi.",
        "translationEn": "This dormitory is very convenient."
      },
      {
        "sentence": "今日はあまり暑くないです。",
        "translation": "Hôm nay trời không nóng lắm.",
        "translationEn": "It is not very hot today."
      },
      {
        "sentence": "ミラーさんはとても元気です。",
        "translation": "Anh Miller rất khỏe mạnh.",
        "translationEn": "Mr. Miller is very energetic."
      },
      {
        "sentence": "あの町はあまり有名じゃありません。",
        "translation": "Thị trấn kia không nổi tiếng lắm.",
        "translationEn": "That town is not very famous."
      }
    ]
  },
  {
    "grammarPoint": "どうですか (Như thế nào)",
    "examples": [
      {
        "sentence": "京都はどうですか。",
        "translation": "Kyoto thế nào?",
        "translationEn": "How is Kyoto?"
      },
      {
        "sentence": "この本はどうですか。…おもしろいです。",
        "translation": "Quyển sách này thế nào? — Thú vị.",
        "translationEn": "How is this book? ...It is interesting."
      },
      {
        "sentence": "日本の食べ物はどうですか。…おいしいです。",
        "translation": "Đồ ăn Nhật thế nào? — Ngon.",
        "translationEn": "How is Japanese food? ...It is delicious."
      },
      {
        "sentence": "その寮はどうですか。…便利です。",
        "translation": "Ký túc xá đó thế nào? — Tiện lợi.",
        "translationEn": "How is that dormitory? ...It is convenient."
      },
      {
        "sentence": "ワット先生はどうですか。…親切です。",
        "translation": "Thầy Watt thế nào? — Tử tế.",
        "translationEn": "How is Mr. Watt? ...He is kind."
      },
      {
        "sentence": "今日はどうですか。…寒いです。",
        "translation": "Hôm nay thế nào? — Trời lạnh.",
        "translationEn": "How is it today? ...It is cold."
      },
      {
        "sentence": "その町はどうですか。…賑やかです。",
        "translation": "Thị trấn đó thế nào? — Nhộn nhịp.",
        "translationEn": "How is that town? ...It is lively."
      },
      {
        "sentence": "この山はどうですか。…高いです。",
        "translation": "Ngọn núi này thế nào? — Cao.",
        "translationEn": "How is this mountain? ...It is high."
      },
      {
        "sentence": "ミラーさんはどうですか。…元気です。",
        "translation": "Anh Miller thế nào? — Khỏe.",
        "translationEn": "How is Mr. Miller? ...He is well."
      },
      {
        "sentence": "このかばんはどうですか。…高いですが、すてきです。",
        "translation": "Cái cặp này thế nào? — Đắt nhưng đẹp.",
        "translationEn": "How is this bag? ...It is expensive, but lovely."
      }
    ]
  },
  {
    "grammarPoint": "どんな N",
    "examples": [
      {
        "sentence": "京都はどんな町ですか。",
        "translation": "Kyoto là thị trấn thế nào?",
        "translationEn": "What kind of town is Kyoto?"
      },
      {
        "sentence": "ワット先生はどんな先生ですか。…親切な先生です。",
        "translation": "Thầy Watt là giáo viên thế nào? — Là giáo viên tử tế.",
        "translationEn": "What kind of teacher is Mr. Watt? ...He is a kind teacher."
      },
      {
        "sentence": "あの山はどんな山ですか。…大きい山です。",
        "translation": "Ngọn núi kia là núi thế nào? — Là ngọn núi lớn.",
        "translationEn": "What kind of mountain is that? ...It is a big mountain."
      },
      {
        "sentence": "どんな食べ物が好きですか。…おいしい食べ物が好きです。",
        "translation": "Bạn thích món ăn thế nào? — Tôi thích món ăn ngon.",
        "translationEn": "What kind of food do you like? ...I like delicious food."
      },
      {
        "sentence": "これはどんな本ですか。…おもしろい本です。",
        "translation": "Đây là quyển sách thế nào? — Là quyển sách thú vị.",
        "translationEn": "What kind of book is this? ...It is an interesting book."
      },
      {
        "sentence": "その寮はどんな寮ですか。…便利な寮です。",
        "translation": "Ký túc xá đó là ký túc xá thế nào? — Là ký túc xá tiện lợi.",
        "translationEn": "What kind of dormitory is that? ...It is a convenient dormitory."
      },
      {
        "sentence": "これはどんなかばんですか。…新しいかばんです。",
        "translation": "Đây là cái cặp thế nào? — Là cái cặp mới.",
        "translationEn": "What kind of bag is this? ...It is a new bag."
      },
      {
        "sentence": "田中さんはどんな人ですか。…元気な人です。",
        "translation": "Anh Tanaka là người thế nào? — Là người khỏe mạnh.",
        "translationEn": "What kind of person is Mr. Tanaka? ...He is an energetic person."
      },
      {
        "sentence": "これはどんな桜ですか。…きれいな桜です。",
        "translation": "Đây là hoa anh đào thế nào? — Là hoa anh đào đẹp.",
        "translationEn": "What kind of cherry blossoms are these? ...They are beautiful cherry blossoms."
      },
      {
        "sentence": "ここはどんな所ですか。…静かな所です。",
        "translation": "Đây là nơi thế nào? — Là nơi yên tĩnh.",
        "translationEn": "What kind of place is this? ...It is a quiet place."
      }
    ]
  }
]
