[
  {
    "grammarPoint": "〜ほど",
    "examples": [
      {
        "sentence": "その映画は何度も見たいほど感動的だった。",
        "translation": "Bộ phim đó cảm động đến mức tôi muốn xem nhiều lần.",
        "translationEn": "That movie was so moving that I wanted to watch it again and again."
      },
      {
        "sentence": "今日は歩けないほど疲れています。",
        "translation": "Hôm nay tôi mệt đến mức không đi nổi.",
        "translationEn": "I am so tired today that I can barely walk."
      },
      {
        "sentence": "この映画は何度も見たくなるほど感動的だった。",
        "translation": "この映画は何度も見たくなるほど感動的だった。",
        "translationEn": "This movie was so moving that I wanted to watch it over and over again."
      },
      {
        "sentence": "彼の演奏は会場が静かになるほど美しかった。",
        "translation": "Màn trình diễn của anh ấy đẹp đến nỗi cả hội trường trở nên im lặng.",
        "translationEn": "His performance was so beautiful that the venue became silent."
      },
      {
        "sentence": "その作品は細かいところまで見たくなるほど面白い。",
        "translation": "Công việc thú vị đến mức bạn muốn xem xét từng chi tiết.",
        "translationEn": "The work is so interesting that you want to look at every detail."
      },
      {
        "sentence": "昨夜のコンサートは、涙が出るほどすばらしかった。",
        "translation": "Buổi hòa nhạc tối qua tuyệt vời đến mức khiến tôi rơi nước mắt.",
        "translationEn": "Last night's concert was so amazing that it brought tears to my eyes."
      },
      {
        "sentence": "あの劇は結末が気になるほど引きこまれた。",
        "translation": "Vở kịch đó đã thu hút tôi đến mức tôi tò mò về cái kết.",
        "translationEn": "That play drew me in so much that I was curious about the ending."
      },
      {
        "sentence": "その絵は本物かと思うほどリアルだった。",
        "translation": "Bức ảnh chân thực đến mức tôi tưởng nó là thật.",
        "translationEn": "The picture was so realistic that I thought it was real."
      },
      {
        "sentence": "この曲は一日中口ずさんでしまうほど印象に残る。",
        "translation": "Bài hát này để lại cho tôi ấn tượng là tôi có thể ngân nga nó suốt cả ngày.",
        "translationEn": "This song leaves an impression on me that I can hum it all day long."
      },
      {
        "sentence": "子どもでも笑うほど分かりやすい演出だった。",
        "translation": "Màn trình diễn dễ hiểu đến mức ngay cả trẻ em cũng phải bật cười.",
        "translationEn": "The performance was so easy to understand that even children laughed."
      }
    ],
    "tags": [
      "vi-human-approved"
    ]
  },
  {
    "grammarPoint": "〜くらい, 〜ぐらい",
    "examples": [
      {
        "sentence": "声が出ないくらい驚いた。",
        "translation": "Tôi ngạc nhiên đến mức không thốt nên lời.",
        "translationEn": "I was so surprised that I could not speak."
      },
      {
        "sentence": "一時間ぐらいなら、待てます。",
        "translation": "Nếu khoảng một tiếng thì tôi có thể đợi.",
        "translationEn": "I can wait for about an hour."
      },
      {
        "sentence": "立っていられないくらい会場が混んでいた。",
        "translation": "Khán phòng đông đến mức tôi không thể đứng nổi.",
        "translationEn": "The venue was so crowded that I couldn't stand."
      },
      {
        "sentence": "朝から晩まで練習したぐらいでは、まだ足りないと思う。",
        "translation": "Tôi không nghĩ chỉ tập luyện từ sáng đến tối là đủ.",
        "translationEn": "I don't think it's enough to just practice from morning until night."
      },
      {
        "sentence": "驚いて声が出ないくらいすごい舞台だった。",
        "translation": "Đó là một màn trình diễn sân khấu tuyệt vời đến nỗi tôi ngạc nhiên đến mức không thể nói nên lời.",
        "translationEn": "It was such an amazing stage performance that I was so surprised that I couldn't even speak."
      },
      {
        "sentence": "その曲はだれでも知っているくらい有名だ。",
        "translation": "Bài hát nổi tiếng đến nỗi ai cũng biết.",
        "translationEn": "The song is so famous that everyone knows it."
      },
      {
        "sentence": "展示室は一日では見切れないくらい広い。",
        "translation": "Phòng triển lãm rộng đến mức bạn không thể xem hết trong một ngày.",
        "translationEn": "The exhibition room is so large that you can't see it all in one day."
      },
      {
        "sentence": "私にでも分かるぐらい説明がていねいだった。",
        "translation": "Lời giải thích chi tiết đến mức ngay cả tôi cũng có thể hiểu được.",
        "translationEn": "The explanation was so detailed that even I could understand it."
      },
      {
        "sentence": "眠れないくらい公演のことが楽しみだった。",
        "translation": "Tôi quá hào hứng với buổi biểu diễn đến nỗi không thể ngủ được.",
        "translationEn": "I was so excited about the performance that I couldn't sleep."
      },
      {
        "sentence": "一人で泣いてしまうぐらい、その場面に感動した。",
        "translation": "Cảnh tượng đó khiến tôi xúc động đến nỗi bật khóc một mình.",
        "translationEn": "I was so moved by that scene that I cried alone."
      }
    ],
    "tags": [
      "vi-human-approved"
    ]
  },
  {
    "grammarPoint": "〜さ",
    "examples": [
      {
        "sentence": "この曲の面白さは、聞くたびに分かってくる。",
        "translation": "Độ thú vị của bài này càng nghe nhiều càng hiểu.",
        "translationEn": "The appeal of this song becomes clearer each time you listen."
      },
      {
        "sentence": "この町の静かさが好きです。",
        "translation": "Tôi thích sự yên tĩnh của thị trấn này.",
        "translationEn": "I like the quietness of this town."
      },
      {
        "sentence": "この曲の深さは、一度聞いただけでは分からない。",
        "translation": "Bạn sẽ không thể biết được chiều sâu của bài hát này nếu chỉ nghe một lần.",
        "translationEn": "You won't know the depth of this song just by listening to it once."
      },
      {
        "sentence": "彼の演技の自然さに驚いた。",
        "translation": "Tôi rất ngạc nhiên trước diễn xuất tự nhiên của anh ấy.",
        "translationEn": "I was surprised at how natural his acting was."
      },
      {
        "sentence": "この映画の面白さは結末だけではない。",
        "translation": "Cái kết không phải là điều duy nhất khiến bộ phim này trở nên thú vị.",
        "translationEn": "The ending isn't the only thing that makes this movie interesting."
      },
      {
        "sentence": "日本の伝統芸能の美しさをもっと知りたい。",
        "translation": "Tôi muốn biết thêm về vẻ đẹp của nghệ thuật biểu diễn truyền thống Nhật Bản.",
        "translationEn": "I want to know more about the beauty of Japanese traditional performing arts."
      },
      {
        "sentence": "その展覧会で色の豊かさを改めて感じた。",
        "translation": "Tại cuộc triển lãm đó, một lần nữa tôi cảm nhận được sự phong phú của màu sắc.",
        "translationEn": "At that exhibition, I once again felt the richness of color."
      },
      {
        "sentence": "この劇場の静かさが作品に合っていた。",
        "translation": "Sự yên tĩnh của nhà hát này phù hợp với công việc.",
        "translationEn": "The quietness of this theater suited the work."
      },
      {
        "sentence": "彼女の声のやわらかさが観客の心に残った。",
        "translation": "Giọng hát nhẹ nhàng của cô đã để lại ấn tượng sâu sắc trong lòng khán giả.",
        "translationEn": "The softness of her voice left a lasting impression on the audience."
      },
      {
        "sentence": "この作品の新しさは音と映像の組み合わせにある。",
        "translation": "Điểm mới lạ của tác phẩm này nằm ở sự kết hợp giữa âm thanh và video.",
        "translationEn": "The novelty of this work lies in the combination of sound and video."
      }
    ],
    "tags": [
      "vi-human-approved"
    ]
  },
  {
    "grammarPoint": "〜ばかりか",
    "examples": [
      {
        "sentence": "その映画は面白いばかりか、音楽もすばらしかった。",
        "translation": "Bộ phim đó không chỉ hay mà âm nhạc cũng tuyệt vời.",
        "translationEn": "That movie was not only interesting, but the music was wonderful too."
      },
      {
        "sentence": "彼は日本語ばかりか、中国語も話せる。",
        "translation": "Anh ấy không chỉ nói được tiếng Nhật mà còn nói được tiếng Trung.",
        "translationEn": "He can speak not only Japanese but also Chinese."
      },
      {
        "sentence": "その俳優は演技ばかりか、歌も上手だ。",
        "translation": "Nam diễn viên không chỉ giỏi diễn xuất mà còn ca hát.",
        "translationEn": "The actor is not only good at acting but also singing."
      },
      {
        "sentence": "この展覧会は子どもばかりか、大人にも人気がある。",
        "translation": "Triển lãm này được yêu thích không chỉ với trẻ em mà cả người lớn.",
        "translationEn": "This exhibition is popular not only with children but also with adults."
      },
      {
        "sentence": "彼は音楽ばかりか、映画にも詳しい。",
        "translation": "Anh ấy không chỉ biết âm nhạc mà còn biết cả phim ảnh.",
        "translationEn": "He knows not only music but also movies."
      },
      {
        "sentence": "その作品は日本ばかりか、海外でも高く評価されている。",
        "translation": "Tác phẩm của ông được đánh giá cao không chỉ ở Nhật Bản mà còn ở nước ngoài.",
        "translationEn": "His works are highly praised not only in Japan but also overseas."
      },
      {
        "sentence": "この曲は美しいばかりか、歌いやすい。",
        "translation": "Bài hát này không chỉ hay mà còn dễ hát.",
        "translationEn": "This song is not only beautiful, but also easy to sing."
      },
      {
        "sentence": "新しい劇場は広いばかりか、音もとてもいい。",
        "translation": "Rạp hát mới không chỉ rộng rãi mà còn có âm thanh tuyệt vời.",
        "translationEn": "The new theater is not only spacious, but also has great sound."
      },
      {
        "sentence": "あの演出家は厳しいばかりか、説明も分かりやすい。",
        "translation": "Vị đạo diễn đó không chỉ nghiêm khắc mà lời giải thích của ông cũng rất dễ hiểu.",
        "translationEn": "That director was not only strict, but his explanations were also easy to understand."
      },
      {
        "sentence": "このイベントは楽しいばかりか、勉強にもなる。",
        "translation": "Sự kiện này không chỉ mang tính giải trí mà còn mang tính giáo dục.",
        "translationEn": "This event is not only fun, but also educational."
      }
    ],
    "tags": [
      "vi-human-approved"
    ]
  }
]
